emfields/__init__.py
emfields-0.0.1.dist-info/DESCRIPTION.rst
emfields-0.0.1.dist-info/METADATA
emfields-0.0.1.dist-info/RECORD
emfields-0.0.1.dist-info/WHEEL
emfields-0.0.1.dist-info/metadata.json
emfields-0.0.1.dist-info/top_level.txt
